{
    "basics": {
        "name": "Jordan",
        "label": "Software Developer",
        "image": "/portfolio/me_avatar.png",
        "email": "sudo.sendmail.jordan@gmail.com",
        "phone": "+1 555-555-5555",
        "url": "https://github.com/sudo-adduser-jordan",
        "summary": "Self starter with a strong aptitude to learn and solve challenges. Ability to further education as needed. Seeking remote work opportunities within the United States.",
        "theme": "blue",
        "location": {
            "address": "",
            "postalCode": "",
            "city": "Remote",
            "countryCode": "US",
            "region": "United States"
        },
        "profiles": [
            {
                "network": "GitHub",
                "username": "sudo-adduser-jordan",
                "url": "https://github.com/sudo-adduser-jordan"
            }
        ]
    },
    "work": [
        {
            "name": "Code Racer",
            "position": "Contributor",
            "location_type": "Remote",
            "location": "United States",
            "url": "https://github.com/webdevcody/code-racer",
            "startDate": "2024-01-01",
            "endDate": "2024-01-01",
            "summary": "Code Racer is a multiplayer coding game where developers can compete against each other to solve programming challenges in real-time.",
            "highlights": [],
            "achievements": [
                "582 forks",
                "700+ stars",
                "Designed and maintained the main feature of the project.",
                "Created tasks and issues, cleared blocking issues, reviewed code, merged pull requests, created complex features."
            ],
            "skills": [
                "Next",
                "React",
                "Tailwind"
            ]
        },
        {
            "name": "Runelite",
            "url": "https://runelite.net/plugin-hub/show/skull-prevention-reminder",
            "position": "Contributor",
            "location_type": "Remote",
            "location": "United States",
            "startDate": "2024-06-01",
            "endDate": "2024-06-01",
            "summary": "Java plugin created with Intellij tooling and the Runelite SDK. A visual indicator of skull prevention status.",
            "achievements": [
                "Active users",
                "1600+ live installs",
                "Third party contributions"
            ],
            "skills": [
                "Java"
            ]
        },
        {
            "name": "Bottles",
            "url": "https://usebottles.com/app/#eveonline",
            "position": "Contributor",
            "location_type": "Remote",
            "location": "United States",
            "startDate": "2024-06-01",
            "endDate": "2024-12-01",
            "summary": "A small but useful contribution to the official Bottles programs. Eve Online launcher.",
            "achievements": [
                "Active users"
            ],
            "skills": [
                "Yaml"
            ]
        }
    ],
    "volunteer": [
        {
            "organization": "organization",
            "position": "Volunteer",
            "url": "https://github.com/",
            "startDate": "2021-01-01",
            "endDate": "2022-01-01",
            "summary": "Helped organize coding workshops and mentored new members.",
            "highlights": [
                "Awarded 'Volunteer of the Month'"
            ]
        }
    ],
    "education": [
        {
            "institution": "State University",
            "url": "https://stateuniversity.edu",
            "area": "Computer Science",
            "studyType": "Bachelor",
            "startDate": "2024-08-01",
            "endDate": "2025-08-01"
        }
    ],
    "certificates": [
        {
            "name": "Java Developer",
            "date": "2023-02-01",
            "issuer": "Jetbrains",
            "url": "https://onlineuniversity.com/certificates/fullstack"
        },
        {
            "name": "Python Developer",
            "date": "2023-02-01",
            "issuer": "Jetbrains",
            "url": "https://onlineuniversity.com/certificates/fullstack"
        },
        {
            "name": "Go Developer",
            "date": "2023-02-01",
            "issuer": "Jetbrains",
            "url": "https://onlineuniversity.com/certificates/fullstack"
        },
        {
            "name": "Linux",
            "date": "2024-02-01",
            "issuer": "Linux Foundation",
            "url": "https://onlineuniversity.com/certificates/fullstack"
        },
        {
            "name": "ITIL",
            "date": "2024-02-01",
            "issuer": "ITIL Foundation",
            "url": "https://onlineuniversity.com/certificates/fullstack"
        }
    ],
    "skills": [
        { "name": "Database Management" },
        { "name": "Web Development" },
        { "name": "UI Design" },
        { "name": "UX Design" },
        { "name": "Linux Development" },
        { "name": "Cloud Management" },
        { "name": "Windows Development" },
        { "name": "Systems Administration" },
        { "name": "Source Control" },
        { "name": "Software Development" },
        { "name": "Desktop Development" },
        { "name": "Game Development" },

        { "name": "GitHub" },
        { "name": "Gitlab" },
        { "name": "Git" },
        { "name": "Java" },
        { "name": "MySQL" },
        { "name": "Node" },
        { "name": "JavaScript" },
        { "name": "TypeScript" },
        { "name": "React" },
        { "name": "HTML" },
        { "name": "CSS" },
        { "name": "Tailwind" },
        { "name": "Next" }
    ],
    "languages": [
        {
            "language": "English",
            "fluency": "Native speaker"
        }
    ],
    "references": [
        {
            "name": "x",
            "reference": "x"
        }
    ],
    "projects": [
        {
            "name": "Algorithm Visualizer",
            "isActive": true,
            "description": "A website that allows you to visualize the common sorting and path finding algorithms.",
            "url": "",
            "github": "https://computer-algorithm-visualizer.vercel.app/",
            "skills": []
        },
        {
            "name": "Console Graphics Engine",
            "isActive": false,
            "description": "Console 3D Graphics Engine.",
            "url": "",
            "github": "https://github.com/sudo-adduser-jordan/console-graphics-engine"
        },
        {
            "name": "Proto Hackers",
            "isActive": false,
            "description": "Java protohackers solutions with tests.",
            "url": "https://protohackers.com",
            "github": "https://github.com/sudo-adduser-jordan/protohackers"
        },
        {
            "name": "Desktop Environment",
            "isActive": true,
            "description": "My personal desktop configuration.",
            "url": "",
            "github": "https://sudo-adduser-jordan.github.io/gentoox-website"
        }
    ]
}